ykyos_mcp/__init__.py
ykyos_mcp/server.py
ykyos_mcp-0.1.3.dist-info/METADATA
ykyos_mcp-0.1.3.dist-info/WHEEL
ykyos_mcp-0.1.3.dist-info/entry_points.txt
ykyos_mcp-0.1.3.dist-info/top_level.txt
ykyos_mcp-0.1.3.dist-info/RECORD
