Metadata-Version: 2.4
Name: ykyos-mcp
Version: 0.1.3
Summary: MCP Server for URL Processing and Image Extraction
Author: YKY
Author-email: YKY <info@ykyos.com>
Classifier: Programming Language :: Python :: 3
Classifier: License :: OSI Approved :: MIT License
Classifier: Operating System :: OS Independent
Requires-Python: >=3.8
Requires-Dist: mcp>=1.4.0
Requires-Dist: aiohttp>=3.8.0
Requires-Dist: aiofiles>=0.8.0
Dynamic: author
